comment/__init__.py
comment/admin.py
comment/apps.py
comment/models.py
comment/tests.py
comment/utils.py
comment/views.py
comment/migrations/0001_initial.py
comment/migrations/0002_auto_20170727_0738.py
comment/migrations/0003_auto_20170801_0739.py
comment/migrations/__init__.py
django_comment-1.0.3.dist-info/DESCRIPTION.rst
django_comment-1.0.3.dist-info/METADATA
django_comment-1.0.3.dist-info/RECORD
django_comment-1.0.3.dist-info/WHEEL
django_comment-1.0.3.dist-info/metadata.json
django_comment-1.0.3.dist-info/top_level.txt
the_comment/__init__.py
the_comment/settings.py
the_comment/urls.py
the_comment/wsgi.py
